benchmarks/__init__.py
benchmarks/bench_cbma.py
nimare/__init__.py
nimare/_version.py
nimare/base.py
nimare/cli.py
nimare/correct.py
nimare/dataset.py
nimare/diagnostics.py
nimare/estimator.py
nimare/exceptions.py
nimare/generate.py
nimare/io.py
nimare/nimads.py
nimare/results.py
nimare/stats.py
nimare/transforms.py
nimare/utils.py
nimare/annotate/__init__.py
nimare/annotate/cogat.py
nimare/annotate/gclda.py
nimare/annotate/lda.py
nimare/annotate/text.py
nimare/annotate/utils.py
nimare/decode/__init__.py
nimare/decode/base.py
nimare/decode/continuous.py
nimare/decode/discrete.py
nimare/decode/encode.py
nimare/decode/utils.py
nimare/extract/__init__.py
nimare/extract/extract.py
nimare/extract/utils.py
nimare/meta/__init__.py
nimare/meta/cbmr.py
nimare/meta/ibma.py
nimare/meta/kernel.py
nimare/meta/models.py
nimare/meta/utils.py
nimare/meta/cbma/__init__.py
nimare/meta/cbma/ale.py
nimare/meta/cbma/base.py
nimare/meta/cbma/mkda.py
nimare/reports/__init__.py
nimare/reports/base.py
nimare/reports/default.yml
nimare/reports/figures.py
nimare/reports/report.tpl
nimare/resources/__init__.py
nimare/resources/database_file_manifest.json
nimare/resources/english_spellings.csv
nimare/resources/filenames.json
nimare/resources/neurosynth_laird_studies.json
nimare/resources/neurosynth_stoplist.txt
nimare/resources/nidm_pain_dset.json
nimare/resources/references.bib
nimare/resources/semantic_knowledge_children.txt
nimare/resources/semantic_relatedness_children.txt
nimare/resources/atlases/Harvard-Oxford-LICENSE
nimare/resources/atlases/HarvardOxford-cort-maxprob-thr25-2mm.nii.gz
nimare/resources/templates/MNI152_2x2x2_brainmask.nii.gz
nimare/resources/templates/tpl-MNI152NLin6Asym_res-01_T1w.nii.gz
nimare/resources/templates/tpl-MNI152NLin6Asym_res-01_desc-brain_mask.nii.gz
nimare/resources/templates/tpl-MNI152NLin6Asym_res-02_T1w.nii.gz
nimare/resources/templates/tpl-MNI152NLin6Asym_res-02_desc-brain_mask.nii.gz
nimare/tests/__init__.py
nimare/tests/conftest.py
nimare-0.8.0.dist-info/LICENSE
nimare-0.8.0.dist-info/METADATA
nimare-0.8.0.dist-info/WHEEL
nimare-0.8.0.dist-info/entry_points.txt
nimare-0.8.0.dist-info/top_level.txt
nimare-0.8.0.dist-info/RECORD
