Metadata-Version: 2.1
Name: nimare
Version: 0.8.0
Summary: NiMARE: Neuroimaging Meta-Analysis Research Environment
Home-page: https://github.com/neurostuff/NiMARE
Author: NiMARE developers
Author-email: tsalo006@fiu.edu
Maintainer: Taylor Salo
Maintainer-email: tsalo006@fiu.edu
License: MIT
Classifier: Development Status :: 3 - Alpha
Classifier: Environment :: Console
Classifier: Intended Audience :: Science/Research
Classifier: License :: OSI Approved :: MIT License
Classifier: Operating System :: OS Independent
Classifier: Programming Language :: Python :: 3.10
Classifier: Programming Language :: Python :: 3.11
Classifier: Programming Language :: Python :: 3.12
Classifier: Programming Language :: Python :: 3.13
Classifier: Programming Language :: Python :: 3.14
Classifier: Topic :: Scientific/Engineering
Requires-Python: >=3.10
License-File: LICENSE
Requires-Dist: cognitiveatlas>=0.1.11
Requires-Dist: fuzzywuzzy
Requires-Dist: jinja2
Requires-Dist: joblib>=1.3.0
Requires-Dist: matplotlib>=3.6.0
Requires-Dist: nibabel>=5.2.0
Requires-Dist: nilearn<0.14,>=0.12.0
Requires-Dist: numba>=0.57.0
Requires-Dist: numpy>=1.22.4
Requires-Dist: pandas>=2.1.4
Requires-Dist: patsy
Requires-Dist: plotly
Requires-Dist: pymare>=0.0.8
Requires-Dist: pyyaml
Requires-Dist: requests
Requires-Dist: ridgeplot
Requires-Dist: scikit-learn>=1.0.0
Requires-Dist: scipy>=1.8.0
Requires-Dist: sparse>=0.13.0
Requires-Dist: statsmodels!=0.13.2
Requires-Dist: tqdm
Provides-Extra: all
Requires-Dist: indexed-gzip>=1.4.0; extra == "all"
Requires-Dist: torch>=2.0; extra == "all"
Requires-Dist: m2r2; extra == "all"
Requires-Dist: matplotlib; extra == "all"
Requires-Dist: mistune; extra == "all"
Requires-Dist: pillow; extra == "all"
Requires-Dist: recommonmark; extra == "all"
Requires-Dist: seaborn; extra == "all"
Requires-Dist: sphinx>=3.5; extra == "all"
Requires-Dist: sphinx-argparse; extra == "all"
Requires-Dist: sphinx-copybutton; extra == "all"
Requires-Dist: sphinx-gallery; extra == "all"
Requires-Dist: sphinx-rtd-theme>=1.3.0; extra == "all"
Requires-Dist: sphinxcontrib-bibtex; extra == "all"
Requires-Dist: sphinxcontrib-mermaid; extra == "all"
Requires-Dist: docutils<0.21,>=0.18.1; extra == "all"
Requires-Dist: coverage>=7.7; extra == "all"
Requires-Dist: coveralls; extra == "all"
Requires-Dist: flake8-black; extra == "all"
Requires-Dist: flake8-docstrings; extra == "all"
Requires-Dist: flake8-isort; extra == "all"
Requires-Dist: pytest; extra == "all"
Requires-Dist: pytest-cov; extra == "all"
Provides-Extra: cbmr
Requires-Dist: torch>=2.0; extra == "cbmr"
Provides-Extra: doc
Requires-Dist: m2r2; extra == "doc"
Requires-Dist: matplotlib; extra == "doc"
Requires-Dist: mistune; extra == "doc"
Requires-Dist: pillow; extra == "doc"
Requires-Dist: recommonmark; extra == "doc"
Requires-Dist: seaborn; extra == "doc"
Requires-Dist: sphinx>=3.5; extra == "doc"
Requires-Dist: sphinx-argparse; extra == "doc"
Requires-Dist: sphinx-copybutton; extra == "doc"
Requires-Dist: sphinx-gallery; extra == "doc"
Requires-Dist: sphinx-rtd-theme>=1.3.0; extra == "doc"
Requires-Dist: sphinxcontrib-bibtex; extra == "doc"
Requires-Dist: sphinxcontrib-mermaid; extra == "doc"
Requires-Dist: docutils<0.21,>=0.18.1; extra == "doc"
Provides-Extra: gzip
Requires-Dist: indexed-gzip>=1.4.0; extra == "gzip"
Provides-Extra: minimum
Requires-Dist: matplotlib==3.6.0; python_version < "3.11" and extra == "minimum"
Requires-Dist: nibabel==5.2.0; python_version < "3.11" and extra == "minimum"
Requires-Dist: nilearn==0.12.0; python_version < "3.11" and extra == "minimum"
Requires-Dist: numpy==1.22.4; python_version < "3.11" and extra == "minimum"
Requires-Dist: pandas==2.2.0; python_version < "3.11" and extra == "minimum"
Requires-Dist: pymare==0.0.8; python_version < "3.11" and extra == "minimum"
Requires-Dist: scikit-learn==1.4.0; python_version < "3.11" and extra == "minimum"
Requires-Dist: scipy==1.8.0; python_version < "3.11" and extra == "minimum"
Requires-Dist: seaborn==0.13.0; python_version < "3.11" and extra == "minimum"
Provides-Extra: tests
Requires-Dist: coverage>=7.7; extra == "tests"
Requires-Dist: coveralls; extra == "tests"
Requires-Dist: flake8-black; extra == "tests"
Requires-Dist: flake8-docstrings; extra == "tests"
Requires-Dist: flake8-isort; extra == "tests"
Requires-Dist: pytest; extra == "tests"
Requires-Dist: pytest-cov; extra == "tests"
